codemodel/__init__.py
codemodel/_installed_version.py
codemodel/_version.py
codemodel/code_model.py
codemodel/dag.py
codemodel/generate_json.py
codemodel/instance.py
codemodel/json_stack.py
codemodel/numpydoc_helper.py
codemodel/script_model.py
codemodel/version.py
codemodel/asttools/__init__.py
codemodel/asttools/function_handling.py
codemodel/asttools/imports.py
codemodel/asttools/rewriters.py
codemodel/asttools/validators.py
codemodel/tests/__init__.py
codemodel/tests/test_code_model.py
codemodel/tests/test_dag.py
codemodel/tests/test_generate_json.py
codemodel/tests/test_json_stack.py
codemodel/tests/test_numpydoc_helper.py
codemodel/tests/test_script_model.py
codemodel/tests/asttools/__init__.py
codemodel/tests/asttools/functions_ast.py
codemodel/tests/asttools/test_function_handling.py
codemodel/tests/asttools/test_imports.py
codemodel/tests/asttools/test_rewriters.py
codemodel/tests/asttools/test_validators.py
codemodel/type_validation/__init__.py
codemodel/type_validation/array_validation.py
codemodel/type_validation/type_validation.py
codemodel-0.0.7.dist-info/LICENSE
codemodel-0.0.7.dist-info/METADATA
codemodel-0.0.7.dist-info/WHEEL
codemodel-0.0.7.dist-info/top_level.txt
codemodel-0.0.7.dist-info/RECORD
