Metadata-Version: 2.1
Name: codemodel
Version: 0.0.7
Summary: Advanced metaprogramming tools
Home-page: https://github.com/dwhswenson/codemodel
License: MIT
Platform: UNKNOWN
Classifier: Development Status :: 2 - Pre-Alpha
Classifier: License :: OSI Approved :: MIT License
Classifier: Intended Audience :: Developers
Classifier: Natural Language :: English
Classifier: Operating System :: POSIX
Classifier: Programming Language :: Python :: 3
Requires-Dist: astor
Requires-Dist: black
Requires-Dist: isort (>=5)
